datasets_genie/__init__.py
datasets_genie/csv_generator.py
datasets_genie/faker_utils.py
datasets_genie/utils.py
datasets_genie-0.1.1.dist-info/WHEEL
datasets_genie-0.1.1.dist-info/LICENSE
datasets_genie-0.1.1.dist-info/METADATA
datasets_genie-0.1.1.dist-info/RECORD
